odoo10_addon_l10n_fr_account_invoice_factur_x-10.0.1.0.0.99.dev4-nspkg.pth
odoo/addons/l10n_fr_account_invoice_factur-x/README.rst
odoo/addons/l10n_fr_account_invoice_factur-x/__init__.py
odoo/addons/l10n_fr_account_invoice_factur-x/__manifest__.py
odoo/addons/l10n_fr_account_invoice_factur-x/i18n/l10n_fr_account_invoice_factur-x.pot
odoo/addons/l10n_fr_account_invoice_factur-x/models/__init__.py
odoo/addons/l10n_fr_account_invoice_factur-x/models/account_invoice.py
odoo/addons/l10n_fr_account_invoice_factur-x/static/description/icon.png
odoo10_addon_l10n_fr_account_invoice_factur_x-10.0.1.0.0.99.dev4.dist-info/METADATA
odoo10_addon_l10n_fr_account_invoice_factur_x-10.0.1.0.0.99.dev4.dist-info/WHEEL
odoo10_addon_l10n_fr_account_invoice_factur_x-10.0.1.0.0.99.dev4.dist-info/namespace_packages.txt
odoo10_addon_l10n_fr_account_invoice_factur_x-10.0.1.0.0.99.dev4.dist-info/top_level.txt
odoo10_addon_l10n_fr_account_invoice_factur_x-10.0.1.0.0.99.dev4.dist-info/RECORD
