Metadata-Version: 2.1
Name: odoo10-addon-l10n-fr-account-invoice-factur-x
Version: 10.0.1.0.0.99.dev4
Summary: France-specific module to generate Factur-X invoices
Home-page: https://github.com/OCA/l10n-france
Author: Akretion,Odoo Community Association (OCA)
Author-email: support@odoo-community.org
License: AGPL-3
Platform: UNKNOWN
Classifier: Programming Language :: Python
Classifier: Framework :: Odoo
Classifier: License :: OSI Approved :: GNU Affero General Public License v3
Requires-Python: ~=2.7
Requires-Dist: odoo10-addon-account-invoice-factur-x
Requires-Dist: odoo10-addon-l10n-fr-siret
Requires-Dist: odoo (<10.1dev,>=10.0)
